lazyid/lazyid.py
lazyid-2.1.0.dist-info/METADATA
lazyid-2.1.0.dist-info/WHEEL
lazyid-2.1.0.dist-info/top_level.txt
lazyid-2.1.0.dist-info/RECORD
