Metadata-Version: 2.4
Name: lazyid
Version: 2.1.0
Summary: Minimal 16-character URL-safe unique ID generator based on a millisecond timestamp and cryptographically secure random bits.
Author-email: niefdev <niefdev@gmail.com>
Maintainer-email: niefdev <niefdev@gmail.com>
License: MIT
Project-URL: Homepage, https://github.com/niefdev/lazyid
Project-URL: Repository, https://github.com/niefdev/lazyid.git
Project-URL: Issues, https://github.com/niefdev/lazyid/issues
Project-URL: Documentation, https://github.com/niefdev/lazyid#readme
Keywords: id,unique-id,short-id,uuid,identifier,base36,timestamp,url-safe,lazyid,python
Classifier: Development Status :: 5 - Production/Stable
Classifier: Intended Audience :: Developers
Classifier: License :: OSI Approved :: MIT License
Classifier: Operating System :: OS Independent
Classifier: Programming Language :: Python :: 3
Classifier: Programming Language :: Python :: 3.7
Classifier: Programming Language :: Python :: 3.8
Classifier: Programming Language :: Python :: 3.9
Classifier: Programming Language :: Python :: 3.10
Classifier: Programming Language :: Python :: 3.11
Classifier: Programming Language :: Python :: 3.12
Classifier: Topic :: Software Development :: Libraries :: Python Modules
Classifier: Topic :: Utilities
Requires-Python: >=3.7
